{
  "kind": "singleType",
  "collectionName": "navbars",
  "info": {
    "singularName": "navbar",
    "pluralName": "navbars",
    "displayName": "Navbar",
    "description": ""
  },
  "options": {
    "draftAndPublish": false
  },
  "attributes": {
    "links": {
      "type": "dynamiczone",
      "components": [
        "page.navbar-multiple-link",
        "page.navbar-link"
      ]
    },
    "categories": {
      "type": "relation",
      "relation": "oneToMany",
      "target": "api::category.category"
    },
    "private_pages": {
      "type": "relation",
      "relation": "oneToMany",
      "target": "api::private-page.private-page"
    }
  }
}
